structify/__init__.py
structify/_base_client.py
structify/_client.py
structify/_compat.py
structify/_constants.py
structify/_exceptions.py
structify/_files.py
structify/_models.py
structify/_qs.py
structify/_resource.py
structify/_response.py
structify/_streaming.py
structify/_types.py
structify/_version.py
structify/pagination.py
structify/py.typed
structify/_utils/__init__.py
structify/_utils/_compat.py
structify/_utils/_datetime_parse.py
structify/_utils/_logs.py
structify/_utils/_proxy.py
structify/_utils/_reflection.py
structify/_utils/_resources_proxy.py
structify/_utils/_streams.py
structify/_utils/_sync.py
structify/_utils/_transform.py
structify/_utils/_typing.py
structify/_utils/_utils.py
structify/lib/.keep
structify/lib/__init__.py
structify/lib/cost_confirmation.py
structify/resources/__init__.py
structify/resources/chat.py
structify/resources/code.py
structify/resources/documents.py
structify/resources/entities.py
structify/resources/external.py
structify/resources/external_dataframe_proxy.py
structify/resources/jobs.py
structify/resources/match.py
structify/resources/nango.py
structify/resources/polars.py
structify/resources/projects.py
structify/resources/public_sessions.py
structify/resources/sandbox.py
structify/resources/scrape.py
structify/resources/server.py
structify/resources/sessions.py
structify/resources/slack.py
structify/resources/sources.py
structify/resources/structure.py
structify/resources/teams.py
structify/resources/whitelabel.py
structify/resources/whitelabel_service.py
structify/resources/wiki.py
structify/resources/workflow.py
structify/resources/workflow_schedule.py
structify/resources/admin/__init__.py
structify/resources/admin/admin.py
structify/resources/admin/chat_templates.py
structify/resources/admin/dataset.py
structify/resources/admin/functional_tests.py
structify/resources/admin/jobs.py
structify/resources/admin/sandbox.py
structify/resources/admin/teams.py
structify/resources/admin/users.py
structifyai-1.173.0.dist-info/METADATA
structifyai-1.173.0.dist-info/WHEEL
structifyai-1.173.0.dist-info/licenses/LICENSE
structifyai-1.173.0.dist-info/RECORD
